flask_redisboard/__init__.py
flask_redisboard/constant.py
flask_redisboard/redisboard.py
flask_redisboard/utils.py
flask_redisboard/static/.DS_Store
flask_redisboard/static/css/.DS_Store
flask_redisboard/static/css/components.css
flask_redisboard/static/css/components.css.map
flask_redisboard/static/css/style.css
flask_redisboard/static/css/style.css.map
flask_redisboard/static/dist/03783c5172ee1ad128c576bf88fac168.eot
flask_redisboard/static/dist/073c2f3ce60eaf69cc2767ef3d989078.svg
flask_redisboard/static/dist/8fdea4e89ac405d9f8db327adb331d8d.svg
flask_redisboard/static/dist/acf50f59802f20d8b45220eaae532a1c.ttf
flask_redisboard/static/dist/b557f56e367e59344ca95f9d1fb44352.svg
flask_redisboard/static/dist/ed2b8bf117160466ba6220a8f1da54a4.ttf
flask_redisboard/static/dist/ef3df98419d143d9617fe163bf4edc0b.eot
flask_redisboard/static/dist/css/font.css
flask_redisboard/static/dist/css/font.js
flask_redisboard/static/dist/css/index.css
flask_redisboard/static/dist/css/index.js
flask_redisboard/static/dist/css/lib.css
flask_redisboard/static/dist/css/lib.js
flask_redisboard/static/dist/css/style.css
flask_redisboard/static/dist/css/style.js
flask_redisboard/static/dist/js/common.js
flask_redisboard/static/dist/js/index.js
flask_redisboard/static/dist/js/scripts.js
flask_redisboard/static/dist/js/stisla.js
flask_redisboard/static/dist/pages/command.js
flask_redisboard/static/dist/pages/config.js
flask_redisboard/static/dist/pages/dashboard.js
flask_redisboard/static/dist/pages/database.js
flask_redisboard/static/dist/pages/keydetail.js
flask_redisboard/static/dist/pages/keydetail_hash.js
flask_redisboard/static/dist/pages/keydetail_list.js
flask_redisboard/static/dist/pages/keydetail_set.js
flask_redisboard/static/dist/pages/keydetail_zset.js
flask_redisboard/static/dist/pages/serverinfo.js
flask_redisboard/static/fonts/nunito-v9-latin-600.eot
flask_redisboard/static/fonts/nunito-v9-latin-600.svg
flask_redisboard/static/fonts/nunito-v9-latin-600.ttf
Flask_Redisboard-0.1.7.dist-info/LICENSE
Flask_Redisboard-0.1.7.dist-info/METADATA
Flask_Redisboard-0.1.7.dist-info/WHEEL
Flask_Redisboard-0.1.7.dist-info/top_level.txt
Flask_Redisboard-0.1.7.dist-info/RECORD
