Metadata-Version: 2.1
Name: Flask-Redisboard
Version: 0.1.7
Summary: A flask extension to support user view and manage redis with beautiful interface.
Home-page: https://github.com/hjlarry/flask-redisboard
Author: hjlarry
Author-email: ultrahe@gmail.com
License: MIT
Keywords: flask extension development redis
Platform: any
Classifier: Development Status :: 3 - Alpha
Classifier: Environment :: Web Environment
Classifier: Intended Audience :: Developers
Classifier: License :: OSI Approved :: MIT License
Classifier: Programming Language :: Python
Classifier: Topic :: Internet :: WWW/HTTP :: Dynamic Content
Classifier: Topic :: Software Development :: Libraries :: Python Modules
Requires-Python: >=3.6
Requires-Dist: Flask
Requires-Dist: redis
Provides-Extra: dev
Requires-Dist: black ; extra == 'dev'
